Metadata-Version: 2.1
Name: kickbot
Version: 0.0.8
Summary: Package for developing kick.com bots
Home-page: https://github.com/lukemvc/kickbot
License: MIT
Requires-Python: >=3.10
License-File: LICENSE
